.gitignore
.pylintrc
.testing.pylintrc
ChangeLog.md
LICENSE
README.md
setup.py
docs/Makefile
docs/conf.py
docs/index.rst
docs/make.bat
docs/_static/favicon.ico
docs/_static/salt-logo.pdf
docs/_themes/saltstack/layout.html
docs/_themes/saltstack/theme.conf
docs/_themes/saltstack/static/base-salt.css
docs/_themes/saltstack/static/css/bootstrap-responsive.css
docs/_themes/saltstack/static/css/bootstrap-responsive.min.css
docs/_themes/saltstack/static/css/bootstrap.css
docs/_themes/saltstack/static/css/bootstrap.min.css
docs/_themes/saltstack/static/css/main.css
docs/_themes/saltstack/static/images/SaltStack-Logo.png
docs/_themes/saltstack/static/images/footerBG.jpg
docs/_themes/saltstack/static/images/socialFB.png
docs/_themes/saltstack/static/images/socialG+.png
docs/_themes/saltstack/static/images/socialGitHub.png
docs/_themes/saltstack/static/images/socialLI.png
docs/_themes/saltstack/static/images/socialTW.png
docs/_themes/saltstack/static/img/carouselLeft.png
docs/_themes/saltstack/static/img/carouselRight.png
docs/_themes/saltstack/static/img/glyphicons-halflings-white.png
docs/_themes/saltstack/static/img/glyphicons-halflings.png
docs/_themes/saltstack/static/img/navCurrentArrow.png
docs/_themes/saltstack/static/js/main.js
docs/_themes/saltstack/static/js/vendor/bootstrap.js
docs/_themes/saltstack/static/js/vendor/bootstrap.min.js
docs/_themes/saltstack/static/js/vendor/jquery-1.9.1.js
docs/_themes/saltstack/static/js/vendor/modernizr-2.6.2-respond-1.1.0.js
docs/_themes/saltstack/static/js/vendor/modernizr-2.6.2-respond-1.1.0.min.js
docs/images/RaetMetaphor.pdf
docs/images/RaetMetaphor.png
docs/images/RaetSaltAlphaArchitecture.pdf
docs/images/RaetSaltAlphaArchitecture.png
docs/topics/Salt_Raet.rst
docs/topics/examples_lane.py
docs/topics/examples_road.py
docs/topics/installation.rst
docs/topics/introduction.rst
docs/topics/tutorial.rst
pkg/rpm/python-raet.spec
pkg/suse/python-raet.changes
pkg/suse/python-raet.spec
raet/__init__.py
raet/__metadata__.py
raet.egg-info/PKG-INFO
raet.egg-info/SOURCES.txt
raet.egg-info/dependency_links.txt
raet.egg-info/requires.txt
raet.egg-info/top_level.txt
